LICENSE.txt
README.md
setup.py
grapple/__init__.py
grapple.egg-info/PKG-INFO
grapple.egg-info/SOURCES.txt
grapple.egg-info/dependency_links.txt
grapple.egg-info/top_level.txt