Metadata-Version: 2.1
Name: grapple
Version: 0.3.0
Summary: Deprecated. Use wagtail-grapple instead
Home-page: https://github.com/torchbox/wagtail-grapple
Author: Jack Peterson
Author-email: <jack@tinybike.net>
License: MIT
Keywords: deprecated
Classifier: Development Status :: 7 - Inactive
License-File: LICENSE.txt
